discord_shared_db/__init__.py
discord_shared_db/auth_enums.py
discord_shared_db/base.py
discord_shared_db/db.py
discord_shared_db/models.py
discord_shared_db/user.py
discord_shared_db/user_auth.py
discord_shared_db/user_session.py
discord_shared_db/card_game/card_data.py
discord_shared_db/card_game/decks.py
discord_shared_db/card_game/raw_card_data.py
discord_shared_db/card_game/tcg_enum.py
discord_shared_db/discord/discord_user.py
discord_shared_db/discord/events.py
discord_shared_db/discord/pixel_art.py
discord_shared_db/discord/rps_stats.py
discord_shared_db/discord/ttt_stats.py
discord_shared_db/discord/user_badge.py
discord_shared_db/util/decorators.py
discord_shared_db-1.1.7.dist-info/licenses/LICENSE
old_versions/17393111d12e_adding_card_card_schema_updated_user_.py
old_versions/17776169982d_updated_enum_enum_type_issue.py
old_versions/1e8734a2113c_create_pixel_data_table_for_real_5.py
old_versions/24cd831c3112_create_pixel_data_table_for_real_3.py
old_versions/281181d752d4_add_pixels_data_table.py
old_versions/2be3a086c503_create_pixel_data_table.py
old_versions/3079d3f22142_create_pixel_data_table_for_real.py
old_versions/3cba87a8b28a_pixel_test.py
old_versions/6396a5a61194_updated_init_to_actually_include_files.py
old_versions/666a5a89e2b0_adding_ttt_stats_to_the_database.py
old_versions/6d20b262418d_create_pixel_data_table_for_real_6.py
old_versions/7950e1cbf4f2_add_ttt_stats_table.py
old_versions/8e015abbe587_update_user_and_add_pixel_data.py
old_versions/9c208ac89073_create_pixel_data_table_for_real_2.py
old_versions/a18b186b0291_add_gray_color.py
old_versions/b58357e1fc2e_create_pixel_data_table_for_real_7.py
old_versions/d34f5f07944f_updated_ttt_name_to_rps.py
old_versions/d8b2f833d33f_create_pixel_data_table_for_real_4.py
old_versions/e976e9d6d502_adding_grey_2.py
discord_shared_db-1.1.7.dist-info/METADATA
discord_shared_db-1.1.7.dist-info/WHEEL
discord_shared_db-1.1.7.dist-info/top_level.txt
discord_shared_db-1.1.7.dist-info/RECORD
