Metadata-Version: 2.4
Name: discord-shared-db
Version: 1.1.7
Summary: Shared SQLAlchemy models and DB utilities for Discord bots
Author-email: Couch Comfy <CouchComfyOfficial@gmail.com>
License: AGPL-3.0-only
License-File: LICENSE
Requires-Dist: sqlalchemy>=2.0
Requires-Dist: asyncpg>=0.29
Requires-Dist: sqlalchemy[asyncio]>=2.0.0
Requires-Dist: pydantic>=2.11.3
Requires-Dist: python-dotenv>=1.0.1
Requires-Dist: alembic>=1.16.2
Dynamic: license-file
